mklists/__init__.py
mklists/apply.py
mklists/backup.py
mklists/cli.py
mklists/config.py
mklists/exceptions.py
mklists/linkify.py
mklists/rules.py
mklists-0.2.dist-info/entry_points.txt
mklists-0.2.dist-info/LICENSE
mklists-0.2.dist-info/WHEEL
mklists-0.2.dist-info/METADATA
mklists-0.2.dist-info/RECORD
